23b1023_bcd_to_7_segment_struct.v
module assignment(x1,x2,x3,x4,a,b,c,d,e,f,g);
input x1,x2,x3,x4;
output a,b,c,d,e,f,g;
wire k1, k2, k3, k4;



not (k1, x1);
not (k2, x2);
not (k3, x3);
not (k4, x4);


//// output   a 
wire t1_a, t2_a, t3_a;
and (t1_a, x2, x4);
and (t2_a, x2, k3);
and (t3_a, k2, k4);

or (a, k1, t1_a, t2_a, t3_a);


////// output  b
wire t1_b, t2_b;
and (t1_b, k3, k4);
and (t2_b, x3, x4);

or (b, k1, x2, t1_b, t2_b);


//// output c
or (c, k1, k2, x3, k4);

//// output d
wire t1_d, t2_d, t3_d, t4_d;
and (t1_d, k2, k3, k4);
and (t2_d, k1, k2, x3);
and (t3_d, k1, x2, x3, k4);
and (t4_d, k1, x2, k3, x4);

or (d, t1_d, t2_d, t3_d, t4_d);


//// output e
wire t1_e, t2_e;
and (t1_e, k1, x3, k4);
and (t2_e, k2, k3, k4);

or (e, t1_e, t2_e);

//// output f
wire t1_f, t2_f, t3_f, t4_f;
and (t1_f, k1, k3, k4);
and (t2_f, x1, k2, k3);
and (t3_f, k1, x2, k3, x4);
and (t4_f, k1, x2, x3, k4);

or (f, t1_f, t2_f, t3_f, t4_f);


///// output g 
wire t1_g, t2_g, t3_g, t4_g;
and (t1_g, x1, k2, k3);
and (t2_g, k1, x2, k3);
and (t3_g, k1, k2, x3);
and (t4_g, k1, x2, x3, k4);

or (g, t1_g, t2_g, t3_g, t4_g);

endmodule

23b1023_tb_bcd_to_7_segment_struct.v
`include "23b1023_bcd_to_7_segment_struct.v"
module assignment_tb;

reg x1, x2, x3, x4;

wire a,b,c,d,e,f,g;

assignment uut(
    .x1(x1),
    .x2(x2),
    .x3(x3),
    .x4(x4),
    .a(a),
    .b(b),
    .c(c),
    .d(d),
    .e(e),
    .f(f),
    .g(g)
);

initial begin
    
    #20 x1=0; x2=0; x3=0; x4=1;

    #20 x1=0; x2=0; x3=1; x4=0;

    #20 x1=0; x2=0; x3=1; x4=1;

    #20 x1=0; x2=1; x3=0; x4=0;

    #20 x1=0; x2=1; x3=0; x4=1;

    #20 x1=0; x2=1; x3=1; x4=0;

    #20 x1=0; x2=1; x3=1; x4=1;

    #20 x1=1; x2=0; x3=0; x4=0;

    #20 x1=1; x2=0; x3=0; x4=1;

    #20 x1=0; x2=0; x3=0; x4=0;
    $finish;
end

initial begin
    $dumpfile("temp.vcd"); 
    $dumpvars(0, assignment_tb);
    $display("Name : Pushpendra Uikey");
    $display("Roll Number : 23b1023");
    $monitor("x1=%b x2=%b x3=%b x4=%b A=%b B=%b C=%b D=%b E=%b F=%b G=%b", x1, x2, x3, x4, a, b, c, d, e, f, g);
end


endmodule

temp.vcd
$date
	Thu Aug  8 16:52:33 2024
$end
$version
	Icarus Verilog
$end
$timescale
	1s
$end
$scope module assignment_tb $end
$var wire 1 ! g $end
$var wire 1 " f $end
$var wire 1 # e $end
$var wire 1 $ d $end
$var wire 1 % c $end
$var wire 1 & b $end
$var wire 1 ' a $end
$var reg 1 ( x1 $end
$var reg 1 ) x2 $end
$var reg 1 * x3 $end
$var reg 1 + x4 $end
$scope module uut $end
$var wire 1 ' a $end
$var wire 1 & b $end
$var wire 1 % c $end
$var wire 1 $ d $end
$var wire 1 # e $end
$var wire 1 " f $end
$var wire 1 ! g $end
$var wire 1 , k1 $end
$var wire 1 - k2 $end
$var wire 1 . k3 $end
$var wire 1 / k4 $end
$var wire 1 0 t1_a $end
$var wire 1 1 t1_b $end
$var wire 1 2 t1_d $end
$var wire 1 3 t1_e $end
$var wire 1 4 t1_f $end
$var wire 1 5 t1_g $end
$var wire 1 6 t2_a $end
$var wire 1 7 t2_b $end
$var wire 1 8 t2_d $end
$var wire 1 9 t2_e $end
$var wire 1 : t2_f $end
$var wire 1 ; t2_g $end
$var wire 1 < t3_a $end
$var wire 1 = t3_d $end
$var wire 1 > t3_f $end
$var wire 1 ? t3_g $end
$var wire 1 @ t4_d $end
$var wire 1 A t4_f $end
$var wire 1 B t4_g $end
$var wire 1 ( x1 $end
$var wire 1 ) x2 $end
$var wire 1 * x3 $end
$var wire 1 + x4 $end
$upscope $end
$upscope $end
$enddefinitions $end
#0
$dumpvars
xB
xA
x@
x?
x>
x=
x<
x;
x:
x9
x8
x7
x6
x5
x4
x3
x2
x1
x0
x/
x.
x-
x,
x+
x*
x)
x(
x'
x&
x%
x$
x#
x"
x!
$end
#20
0$
0"
01
0#
0<
02
09
1'
04
0!
0/
1.
07
1%
08
03
0?
1-
00
06
1&
0=
0@
0>
0A
0;
0B
1,
0:
05
1+
0*
0)
0(
#40
1#
1<
13
1$
1!
1/
0.
18
1?
0+
1*
#60
0#
0<
03
0/
17
1+
#80
1"
16
11
14
1;
0$
1!
1/
1.
07
08
0?
0-
0+
0*
1)
#100
01
04
1$
0/
10
1@
1>
1+
#120
1#
1=
13
1A
1B
1$
1"
06
0;
1/
00
0@
0>
0.
0+
1*
#140
0$
0#
0"
0!
0=
03
0A
0B
0/
10
17
1+
#160
1$
1#
1"
1!
11
1&
1<
12
19
1:
15
1'
1/
1.
07
1-
00
0,
0+
0*
0)
1(
#180
0'
0&
0$
0#
0<
01
02
09
0/
1+
#200
1$
1#
1<
11
12
19
1'
1&
14
1"
0!
1/
1,
0:
05
0+
0(
